netk/__init__.py
netk/attribute.py
netk/base.py
netk/core.py
netk/object.py
netkit/__init__.py
netk-0.1.3.dist-info/METADATA
netk-0.1.3.dist-info/WHEEL
netk-0.1.3.dist-info/RECORD
